sqlite_utils_sqlite_robotstxt/__init__.py
sqlite_utils_sqlite_robotstxt/version.py
sqlite_utils_sqlite_robotstxt-0.0.1a3.dist-info/METADATA
sqlite_utils_sqlite_robotstxt-0.0.1a3.dist-info/WHEEL
sqlite_utils_sqlite_robotstxt-0.0.1a3.dist-info/entry_points.txt
sqlite_utils_sqlite_robotstxt-0.0.1a3.dist-info/top_level.txt
sqlite_utils_sqlite_robotstxt-0.0.1a3.dist-info/RECORD
