Metadata-Version: 2.1
Name: sqlite-utils-sqlite-robotstxt
Version: 0.0.1a3
Summary: TODO
Author: Alex Garcia
License: Apache-2.0
Project-URL: Homepage, https://github.com/asg017/sqlite-robotstxt
Project-URL: Changelog, https://github.com/asg017/sqlite-robotstxt/releases
Project-URL: Issues, https://github.com/asg017/sqlite-robotstxt/issues
Requires-Dist: sqlite-utils
Requires-Dist: sqlite-robotstxt
